unparallel/__init__.py
unparallel/unparallel.py
unparallel/utils.py
unparallel-0.4.0.dist-info/LICENSE
unparallel-0.4.0.dist-info/METADATA
unparallel-0.4.0.dist-info/WHEEL
unparallel-0.4.0.dist-info/RECORD
