Metadata-Version: 2.1
Name: unparallel
Version: 0.4.0
Summary: Create async web requests in no time
Home-page: https://github.com/RafaelWO/unparallel
License: MIT
Keywords: async,http,requests,network
Author: RafaelWO
Author-email: weingartner.rafael@hotmail.com
Requires-Python: >=3.8,<4.0
Classifier: Development Status :: 4 - Beta
Classifier: Intended Audience :: Developers
Classifier: License :: OSI Approved :: MIT License
Classifier: Operating System :: OS Independent
Classifier: Programming Language :: Python :: 3
Classifier: Programming Language :: Python :: 3.8
Classifier: Programming Language :: Python :: 3.9
Classifier: Programming Language :: Python :: 3.10
Classifier: Programming Language :: Python :: 3.11
Classifier: Programming Language :: Python :: 3.12
Classifier: Topic :: Software Development :: Libraries :: Python Modules
Requires-Dist: httpx (>=0.21.0)
Requires-Dist: tqdm (>=4.61.2)
Project-URL: Repository, https://github.com/RafaelWO/unparallel
